githarvest/__init__.py
githarvest-0.1.0.dist-info/LICENSE
githarvest-0.1.0.dist-info/METADATA
githarvest-0.1.0.dist-info/WHEEL
githarvest-0.1.0.dist-info/RECORD
